dunderlab/djangoship/__init__.py
dunderlab_djangoship-0.1a11.data/scripts/djangoship
dunderlab_djangoship-0.1a11.dist-info/METADATA
dunderlab_djangoship-0.1a11.dist-info/WHEEL
dunderlab_djangoship-0.1a11.dist-info/top_level.txt
dunderlab_djangoship-0.1a11.dist-info/RECORD
